{
  "patients": [
    {
      "id": 1,
      "area": "urban",
      "firstName": "Herbie",
      "lastName": "Usmar",
      "email": "husmar0@gravatar.com",
      "gender": "Male",
      "phone": "+86 (146) 661-6804",
      "city": "Bayart Huxu",
      "job": "Professor",
      "address": "195 Norway Maple Center",
      "age": 83,
      "idn": "0079691919",
      "diagnosis": "Myrmecophaga tridactyla"
    },
    {
      "id": 2,
      "area": "urban",
      "firstName": "Caryl",
      "lastName": "Wykey",
      "email": "cwykey1@nsw.gov.au",
      "gender": "Male",
      "phone": "+1 (423) 404-1278",
      "city": "Johnson City",
      "job": "Paralegal",
      "address": "2928 Mariners Cove Road",
      "age": 63,
      "idn": "5217890649",
      "diagnosis": "Pitangus sulphuratus"
    },
    {
      "id": 3,
      "area": "urban",
      "firstName": "Nicolis",
      "lastName": "Vuitte",
      "email": "nvuitte2@noaa.gov",
      "gender": "Male",
      "phone": "+258 (242) 940-7383",
      "city": "Maxixe",
      "job": "Teacher",
      "address": "48974 Independence Pass",
      "age": 40,
      "idn": "5623631738",
      "diagnosis": "unavailable"
    },
    {
      "id": 4,
      "area": "urban",
      "firstName": "Dulcinea",
      "lastName": "De Santos",
      "email": "ddesantos3@ebay.co.uk",
      "gender": "Female",
      "phone": "+51 (185) 750-9200",
      "city": "Santo Tomas",
      "job": "Information Systems Manager",
      "address": "0725 Memorial Park",
      "age": 54,
      "idn": "7712561176",
      "diagnosis": "Dasypus septemcincus"
    },
    {
      "id": 5,
      "area": "urban",
      "firstName": "Flossi",
      "lastName": "Yankov",
      "email": "fyankov4@businessinsider.com",
      "gender": "Female",
      "phone": "+62 (208) 419-2853",
      "city": "Kebonan",
      "job": "Systems Administrator IV",
      "address": "86 Monica Terrace",
      "age": 47,
      "idn": "3312868610",
      "diagnosis": "Pycnonotus nigricans"
    },
    {
      "id": 6,
      "area": "urban",
      "firstName": "Cherilyn",
      "lastName": "Imlin",
      "email": "cimlin5@dion.ne.jp",
      "gender": "Female",
      "phone": "+1 (573) 306-8781",
      "city": "Lunenburg",
      "job": "Safety Technician I",
      "address": "388 Valley Edge Street",
      "age": 51,
      "idn": "6609168008",
      "diagnosis": "Kobus defassa"
    },
    {
      "id": 7,
      "area": "urban",
      "firstName": "Ardelle",
      "lastName": "Townend",
      "email": "atownend6@umn.edu",
      "gender": "Female",
      "phone": "+86 (548) 926-1193",
      "city": "Xinbao",
      "job": "Nurse",
      "address": "72712 Delaware Point",
      "age": 80,
      "idn": "8058268445",
      "diagnosis": "Ratufa indica"
    },
    {
      "id": 8,
      "area": "urban",
      "firstName": "Cindy",
      "lastName": "Wardhaw",
      "email": "cwardhaw7@google.fr",
      "gender": "Female",
      "phone": "+62 (420) 756-2879",
      "city": "Kubangkondang",
      "job": "Paralegal",
      "address": "038 Eastlawn Point",
      "age": 77,
      "idn": "2505307016",
      "diagnosis": "Hymenolaimus malacorhynchus"
    },
    {
      "id": 9,
      "area": "urban",
      "firstName": "Bevin",
      "lastName": "Aburrow",
      "email": "baburrow8@cargocollective.com",
      "gender": "Male",
      "phone": "+46 (453) 473-4632",
      "city": "Vällingby",
      "job": "Safety Technician III",
      "address": "1 Reinke Point",
      "age": 32,
      "idn": "5822644139",
      "diagnosis": "Dusicyon thous"
    },
    {
      "id": 10,
      "area": "urban",
      "firstName": "Chloe",
      "lastName": "Mountjoy",
      "email": "cmountjoy9@bloomberg.com",
      "gender": "Female",
      "phone": "+86 (488) 123-2819",
      "city": "Beihuaidian",
      "job": "Web Designer II",
      "address": "65 Transport Avenue",
      "age": 24,
      "idn": "9362160676",
      "diagnosis": "Merops nubicus"
    },
    {
      "id": 11,
      "area": "urban",
      "firstName": "Maddie",
      "lastName": "Jessel",
      "email": "mjessela@hubpages.com",
      "gender": "Male",
      "phone": "+33 (929) 700-6666",
      "city": "Quimper",
      "job": "Health Coach II",
      "address": "383 Mesta Plaza",
      "age": 89,
      "idn": "0070741395",
      "diagnosis": "Varanus sp."
    },
    {
      "id": 12,
      "area": "urban",
      "firstName": "Allx",
      "lastName": "Waplington",
      "email": "awaplingtonb@devhub.com",
      "gender": "Female",
      "phone": "+86 (333) 891-4435",
      "city": "Gaohe",
      "job": "Software Consultant",
      "address": "7 Rutledge Hill",
      "age": 88,
      "idn": "8198987509",
      "diagnosis": "Philetairus socius"
    },
    {
      "id": 13,
      "area": "urban",
      "firstName": "Kearney",
      "lastName": "McLevie",
      "email": "kmcleviec@jimdo.com",
      "gender": "Male",
      "phone": "+66 (878) 675-3288",
      "city": "Lamduan",
      "job": "Product Engineer",
      "address": "18 Milwaukee Junction",
      "age": 65,
      "idn": "8136321086",
      "diagnosis": "Cervus canadensis"
    },
    {
      "id": 14,
      "area": "urban",
      "firstName": "Scott",
      "lastName": "McNeely",
      "email": "smcneelyd@va.gov",
      "gender": "Male",
      "phone": "+55 (691) 635-6675",
      "city": "Mangaratiba",
      "job": "Human Resources Assistant II",
      "address": "65412 Shelley Avenue",
      "age": 32,
      "idn": "5392872824",
      "diagnosis": "Tyto novaehollandiae"
    },
    {
      "id": 15,
      "area": "urban",
      "firstName": "Britt",
      "lastName": "Copplestone",
      "email": "bcopplestonee@de.vu",
      "gender": "Polygender",
      "phone": "+351 (118) 563-8200",
      "city": "Jardoeira",
      "job": "Safety Technician III",
      "address": "9 Maywood Plaza",
      "age": 76,
      "idn": "5396472103",
      "diagnosis": "Carduelis pinus"
    },
    {
      "id": 16,
      "area": "urban",
      "firstName": "Frasco",
      "lastName": "Dacke",
      "email": "fdackef@chronoengine.com",
      "gender": "Male",
      "phone": "+33 (253) 352-9701",
      "city": "Briey",
      "job": "Human Resources Manager",
      "address": "48613 Crownhardt Circle",
      "age": 46,
      "idn": "3538150095",
      "diagnosis": "Varanus sp."
    },
    {
      "id": 17,
      "area": "urban",
      "firstName": "Orren",
      "lastName": "Herculson",
      "email": "oherculsong@so-net.ne.jp",
      "gender": "Male",
      "phone": "+7 (922) 771-0605",
      "city": "Podosinovets",
      "job": "Research Nurse",
      "address": "375 Gerald Center",
      "age": 21,
      "idn": "3984941196",
      "diagnosis": "Lophoaetus occipitalis"
    },
    {
      "id": 18,
      "area": "urban",
      "firstName": "Les",
      "lastName": "Denkel",
      "email": "ldenkelh@ftc.gov",
      "gender": "Bigender",
      "phone": "+60 (725) 185-0770",
      "city": "Kuala Lumpur",
      "job": "Nuclear Power Engineer",
      "address": "036 Corscot Trail",
      "age": 22,
      "idn": "9927926650",
      "diagnosis": "Phoenicopterus ruber"
    },
    {
      "id": 19,
      "area": "urban",
      "firstName": "Catina",
      "lastName": "Echalie",
      "email": "cechaliei@omniture.com",
      "gender": "Female",
      "phone": "+251 (839) 154-9941",
      "city": "Yirga ‘Alem",
      "job": "Programmer II",
      "address": "94 Mallory Point",
      "age": 31,
      "idn": "7376136150",
      "diagnosis": "Haliaetus leucogaster"
    },
    {
      "id": 20,
      "area": "urban",
      "firstName": "Gilberta",
      "lastName": "Mayfield",
      "email": "gmayfieldj@ibm.com",
      "gender": "Female",
      "phone": "+260 (784) 873-3116",
      "city": "Isoka",
      "job": "Actuary",
      "address": "283 Summit Trail",
      "age": 59,
      "idn": "5857247659",
      "diagnosis": "Francolinus coqui"
    },
    {
      "id": 21,
      "area": "urban",
      "firstName": "Emiline",
      "lastName": "Cornford",
      "email": "ecornfordk@tiny.cc",
      "gender": "Female",
      "phone": "+86 (580) 386-3310",
      "city": "Tangzha",
      "job": "Administrative Assistant III",
      "address": "08914 Chinook Lane",
      "age": 74,
      "idn": "1890671525",
      "diagnosis": "Semnopithecus entellus"
    },
    {
      "id": 22,
      "area": "urban",
      "firstName": "Laurianne",
      "lastName": "Sugge",
      "email": "lsuggel@seesaa.net",
      "gender": "Female",
      "phone": "+51 (826) 365-1526",
      "city": "Cabanilla",
      "job": "Quality Control Specialist",
      "address": "3 East Center",
      "age": 81,
      "idn": "5382839085",
      "diagnosis": "Varanus salvator"
    },
    {
      "id": 23,
      "area": "urban",
      "firstName": "Griswold",
      "lastName": "Pavlishchev",
      "email": "gpavlishchevm@va.gov",
      "gender": "Male",
      "phone": "+251 (284) 665-4711",
      "city": "Debark’",
      "job": "Executive Secretary",
      "address": "94978 Havey Hill",
      "age": 22,
      "idn": "9976239440",
      "diagnosis": "Pavo cristatus"
    },
    {
      "id": 24,
      "area": "urban",
      "firstName": "Scarlet",
      "lastName": "Monkley",
      "email": "smonkleyn@gizmodo.com",
      "gender": "Female",
      "phone": "+63 (521) 548-8003",
      "city": "Ogod",
      "job": "financial Advisor",
      "address": "2642 8th Hill",
      "age": 32,
      "idn": "8417573801",
      "diagnosis": "Coluber constrictor"
    },
    {
      "id": 25,
      "area": "urban",
      "firstName": "Hilary",
      "lastName": "finneran",
      "email": "hfinnerano@blogs.com",
      "gender": "Male",
      "phone": "+47 (708) 830-5182",
      "city": "Bergen",
      "job": "Structural Analysis Engineer",
      "address": "8 Northridge Alley",
      "age": 22,
      "idn": "1853478490",
      "diagnosis": "Potos flavus"
    },
    {
      "id": 26,
      "area": "urban",
      "firstName": "Tyne",
      "lastName": "Mesias",
      "email": "tmesiasp@theatlantic.com",
      "gender": "Non-binary",
      "phone": "+7 (582) 776-9319",
      "city": "Safakulevo",
      "job": "Staff Accountant III",
      "address": "82969 Morrow Park",
      "age": 61,
      "idn": "2580794794",
      "diagnosis": "Lorythaixoides concolor"
    },
    {
      "id": 27,
      "area": "urban",
      "firstName": "Estel",
      "lastName": "Alsina",
      "email": "ealsinaq@dedecms.com",
      "gender": "Female",
      "phone": "+351 (951) 875-3435",
      "city": "Sá",
      "job": "Business Systems Development Analyst",
      "address": "550 Garrison Drive",
      "age": 22,
      "idn": "8469552333",
      "diagnosis": "Ratufa indica"
    },
    {
      "id": 28,
      "area": "urban",
      "firstName": "Edy",
      "lastName": "Murison",
      "email": "emurisonr@so-net.ne.jp",
      "gender": "Female",
      "phone": "+691 (950) 273-8721",
      "city": "Moch",
      "job": "Actuary",
      "address": "2227 Westerfield Trail",
      "age": 25,
      "idn": "3235487131",
      "diagnosis": "Lycaon pictus"
    },
    {
      "id": 29,
      "area": "urban",
      "firstName": "Antone",
      "lastName": "Croisier",
      "email": "acroisiers@state.tx.us",
      "gender": "Male",
      "phone": "+62 (133) 503-6348",
      "city": "Parigi",
      "job": "Software Test Engineer III",
      "address": "7726 Sullivan Center",
      "age": 60,
      "idn": "3746024730",
      "diagnosis": "Dipodomys deserti"
    },
    {
      "id": 30,
      "area": "urban",
      "firstName": "Inglebert",
      "lastName": "Curtis",
      "email": "icurtist@berkeley.edu",
      "gender": "Male",
      "phone": "+62 (179) 381-8813",
      "city": "Kedungtaman",
      "job": "Research Assistant I",
      "address": "08 Londonderry Drive",
      "age": 42,
      "idn": "8078519575",
      "diagnosis": "Tyto novaehollandiae"
    },
    {
      "id": 31,
      "area": "urban",
      "firstName": "Rutherford",
      "lastName": "Pulham",
      "email": "rpulhamu@webmd.com",
      "gender": "Genderfluid",
      "phone": "+7 (736) 893-4289",
      "city": "Borzoy",
      "job": "General Manager",
      "address": "71 Schurz Way",
      "age": 45,
      "idn": "3394336936",
      "diagnosis": "Cercatetus concinnus"
    },
    {
      "id": 32,
      "area": "urban",
      "firstName": "Whitney",
      "lastName": "Lummasana",
      "email": "wlummasanav@narod.ru",
      "gender": "Male",
      "phone": "+598 (246) 548-9909",
      "city": "Soca",
      "job": "Product Engineer",
      "address": "52 School Park",
      "age": 59,
      "idn": "0024350141",
      "diagnosis": "Boa constrictor mexicana"
    },
    {
      "id": 33,
      "area": "urban",
      "firstName": "Bobbi",
      "lastName": "Feckey",
      "email": "bfeckeyw@ebay.com",
      "gender": "Female",
      "phone": "+993 (415) 513-9100",
      "city": "Gowurdak",
      "job": "Recruiting Manager",
      "address": "46190 Forest Dale Place",
      "age": 88,
      "idn": "4367153541",
      "diagnosis": "Eutamias minimus"
    },
    {
      "id": 34,
      "area": "urban",
      "firstName": "Timofei",
      "lastName": "Cabral",
      "email": "tcabralx@bloomberg.com",
      "gender": "Male",
      "phone": "+46 (747) 371-8386",
      "city": "Oskarshamn",
      "job": "financial Analyst",
      "address": "9 Anhalt Road",
      "age": 23,
      "idn": "5684904130",
      "diagnosis": "Varanus sp."
    },
    {
      "id": 35,
      "area": "urban",
      "firstName": "Lorelle",
      "lastName": "Struijs",
      "email": "lstruijsy@diigo.com",
      "gender": "Non-binary",
      "phone": "+380 (457) 826-2969",
      "city": "Komsomol’s’ke",
      "job": "Business Systems Development Analyst",
      "address": "87 Fremont Parkway",
      "age": 56,
      "idn": "0971477140",
      "diagnosis": "Anathana ellioti"
    },
    {
      "id": 36,
      "area": "urban",
      "firstName": "Emilee",
      "lastName": "Watterson",
      "email": "ewattersonz@dropbox.com",
      "gender": "Female",
      "phone": "+60 (543) 888-7878",
      "city": "Alor Setar",
      "job": "Professor",
      "address": "35770 Eliot Point",
      "age": 45,
      "idn": "7696563238",
      "diagnosis": "Lycosa godeffroyi"
    },
    {
      "id": 37,
      "area": "urban",
      "firstName": "Susannah",
      "lastName": "Kinane",
      "email": "skinane10@gmpg.org",
      "gender": "Agender",
      "phone": "+62 (445) 566-4894",
      "city": "Girijaya",
      "job": "Software Engineer I",
      "address": "6 5th Park",
      "age": 43,
      "idn": "0079049656",
      "diagnosis": "Cacatua galerita"
    },
    {
      "id": 38,
      "area": "urban",
      "firstName": "Aldous",
      "lastName": "Shervil",
      "email": "ashervil11@storify.com",
      "gender": "Male",
      "phone": "+86 (740) 525-4275",
      "city": "Tuanjie",
      "job": "Computer Systems Analyst II",
      "address": "16018 Fremont Trail",
      "age": 79,
      "idn": "5660602800",
      "diagnosis": "Petaurus breviceps"
    },
    {
      "id": 39,
      "area": "urban",
      "firstName": "Filip",
      "lastName": "Avarne",
      "email": "favarne12@bluehost.com",
      "gender": "Male",
      "phone": "+62 (984) 216-0580",
      "city": "Sembung",
      "job": "Staff Scientist",
      "address": "002 Stang Trail",
      "age": 27,
      "idn": "4599918148",
      "diagnosis": "Equus hemionus"
    },
    {
      "id": 40,
      "area": "urban",
      "firstName": "Waring",
      "lastName": "Pemble",
      "email": "wpemble13@cdc.gov",
      "gender": "Male",
      "phone": "+63 (207) 238-2394",
      "city": "Silago",
      "job": "Accountant I",
      "address": "93 Sauthoff Center",
      "age": 80,
      "idn": "9195001530",
      "diagnosis": "Chamaelo sp."
    },
    {
      "id": 41,
      "area": "urban",
      "firstName": "Alden",
      "lastName": "Romanelli",
      "email": "aromanelli14@imdb.com",
      "gender": "Male",
      "phone": "+381 (731) 430-3893",
      "city": "Šabac",
      "job": "Health Coach II",
      "address": "81 Ronald Regan Hill",
      "age": 71,
      "idn": "0810961385",
      "diagnosis": "Cervus elaphus"
    },
    {
      "id": 42,
      "area": "urban",
      "firstName": "Odelle",
      "lastName": "Nilges",
      "email": "onilges15@bizjournals.com",
      "gender": "Female",
      "phone": "+62 (779) 989-6028",
      "city": "Rerawere",
      "job": "Database Administrator III",
      "address": "85079 Weeping Birch Place",
      "age": 20,
      "idn": "2984691954",
      "diagnosis": "Spermophilus lateralis"
    },
    {
      "id": 43,
      "area": "urban",
      "firstName": "Lenora",
      "lastName": "Chancellor",
      "email": "lchancellor16@webmd.com",
      "gender": "Female",
      "phone": "+86 (823) 389-5019",
      "city": "Fengping",
      "job": "Speech Pathologist",
      "address": "095 Grasskamp Street",
      "age": 43,
      "idn": "2060942101",
      "diagnosis": "Canis lupus"
    },
    {
      "id": 44,
      "area": "urban",
      "firstName": "Penni",
      "lastName": "McFaell",
      "email": "pmcfaell17@technorati.com",
      "gender": "Female",
      "phone": "+86 (234) 879-5029",
      "city": "Nu’erbage",
      "job": "Information Systems Manager",
      "address": "285 Old Gate Road",
      "age": 46,
      "idn": "8089807275",
      "diagnosis": "Tragelaphus angasi"
    },
    {
      "id": 45,
      "area": "urban",
      "firstName": "Romola",
      "lastName": "Dendle",
      "email": "rdendle18@facebook.com",
      "gender": "Female",
      "phone": "+63 (677) 293-3620",
      "city": "Sinacaban",
      "job": "Graphic Designer",
      "address": "205 Prentice Avenue",
      "age": 69,
      "idn": "3192351047",
      "diagnosis": "Tauraco porphyrelophus"
    },
    {
      "id": 46,
      "area": "urban",
      "firstName": "Walt",
      "lastName": "Ramet",
      "email": "wramet19@barnesandnoble.com",
      "gender": "Agender",
      "phone": "+66 (526) 664-8138",
      "city": "Yala",
      "job": "Director of Sales",
      "address": "9371 Independence Street",
      "age": 86,
      "idn": "5266380578",
      "diagnosis": "Leptoptilus dubius"
    },
    {
      "id": 47,
      "area": "urban",
      "firstName": "Alisander",
      "lastName": "Gooley",
      "email": "agooley1a@domainmarket.com",
      "gender": "Male",
      "phone": "+98 (450) 529-8202",
      "city": "Zābolī",
      "job": "Compensation Analyst",
      "address": "120 Pennsylvania Center",
      "age": 70,
      "idn": "6145360712",
      "diagnosis": "Panthera pardus"
    },
    {
      "id": 48,
      "area": "urban",
      "firstName": "Victor",
      "lastName": "Dahill",
      "email": "vdahill1b@si.edu",
      "gender": "Male",
      "phone": "+45 (807) 848-0452",
      "city": "Frederiksberg",
      "job": "Internal Auditor",
      "address": "39 Vera Center",
      "age": 86,
      "idn": "9954825673",
      "diagnosis": "Ursus americanus"
    },
    {
      "id": 49,
      "area": "urban",
      "firstName": "Franny",
      "lastName": "Espina",
      "email": "fespina1c@over-blog.com",
      "gender": "Male",
      "phone": "+86 (824) 980-3182",
      "city": "Guoyuan",
      "job": "Teacher",
      "address": "6 Straubel Parkway",
      "age": 26,
      "idn": "3523308887",
      "diagnosis": "Larus dominicanus"
    },
    {
      "id": 50,
      "area": "urban",
      "firstName": "Suzy",
      "lastName": "Applebee",
      "email": "sapplebee1d@squidoo.com",
      "gender": "Genderqueer",
      "phone": "+420 (341) 492-9622",
      "city": "Šilheřovice",
      "job": "Civil Engineer",
      "address": "21 Melody Parkway",
      "age": 77,
      "idn": "8233409197",
      "diagnosis": "Macaca radiata"
    }
  ],
  "appointments": [
    {
      "id": 104,
      "procedure": "Reevaluare",
      "time": "09:00-09:30",
      "patient": {
        "id": 1,
        "firstName": "Herbie",
        "lastName": "Usmar",
        "email": "husmar0@gravatar.com",
        "gender": "Male",
        "phone": "+86 (146) 661-6804",
        "city": "Bayart Huxu",
        "job": "Professor",
        "address": "195 Norway Maple Center",
        "age": 83,
        "idn": "0079691919",
        "diagnosis": "Myrmecophaga tridactyla"
      },
      "date": "2023-03-06T22:00:00.000Z",
      "history": "",
      "treatment": ""
    },
    {
      "id": 105,
      "procedure": "Reevaluare",
      "time": "08:30-09:00",
      "patient": {
        "id": 2,
        "firstName": "Caryl",
        "lastName": "Wykey",
        "email": "cwykey1@nsw.gov.au",
        "gender": "Male",
        "phone": "+1 (423) 404-1278",
        "city": "Johnson City",
        "job": "Paralegal",
        "address": "2928 Mariners Cove Road",
        "age": 63,
        "idn": "5217890649",
        "diagnosis": "Pitangus sulphuratus"
      },
      "date": "2023-03-06T22:00:00.000Z",
      "history": "",
      "treatment": ""
    },
    {
      "id": 106,
      "procedure": "Reevaluare",
      "time": "09:30-10:00",
      "patient": {
        "id": 5,
        "firstName": "Flossi",
        "lastName": "Yankov",
        "email": "fyankov4@businessinsider.com",
        "gender": "Female",
        "phone": "+62 (208) 419-2853",
        "city": "Kebonan",
        "job": "Systems Administrator IV",
        "address": "86 Monica Terrace",
        "age": 47,
        "idn": "3312868610",
        "diagnosis": "Pycnonotus nigricans"
      },
      "date": "2023-03-07T22:00:00.000Z",
      "history": "",
      "treatment": ""
    },
    {
      "id": 107,
      "procedure": "Punctie",
      "time": "11:30-12:00",
      "patient": {
        "id": 10,
        "firstName": "Chloe",
        "lastName": "Mountjoy",
        "email": "cmountjoy9@bloomberg.com",
        "gender": "Female",
        "phone": "+86 (488) 123-2819",
        "city": "Beihuaidian",
        "job": "Web Designer II",
        "address": "65 Transport Avenue",
        "age": 24,
        "idn": "9362160676",
        "diagnosis": "Merops nubicus"
      },
      "date": "2023-03-07T22:00:00.000Z",
      "history": "",
      "treatment": ""
    },
    {
      "id": 109,
      "procedure": "Reevaluare",
      "time": "09:00-09:30",
      "patient": {
        "id": 2,
        "firstName": "Caryl",
        "lastName": "Wykey",
        "email": "cwykey1@nsw.gov.au",
        "gender": "Male",
        "phone": "+1 (423) 404-1278",
        "city": "Johnson City",
        "job": "Paralegal",
        "address": "2928 Mariners Cove Road",
        "age": 63,
        "idn": "5217890649",
        "diagnosis": "Pitangus sulphuratus"
      },
      "date": "2023-03-07T22:00:00.000Z",
      "history": "",
      "treatment": ""
    },
    {
      "id": 110,
      "procedure": "Initial Evaluation",
      "time": "8:00-8:30",
      "patient": {
        "id": 12,
        "area": "urban",
        "firstName": "Allx",
        "lastName": "Waplington",
        "email": "awaplingtonb@devhub.com",
        "gender": "Female",
        "phone": "+86 (333) 891-4435",
        "city": "Gaohe",
        "job": "Software Consultant",
        "address": "7 Rutledge Hill",
        "age": 88,
        "idn": "8198987509",
        "diagnosis": "Philetairus socius"
      },
      "date": "2023-03-08T22:00:00.000Z",
      "history": "",
      "treatment": "",
      "diagnosis": "",
      "clinicalExam": ""
    },
    {
      "id": 111,
      "procedure": "Reevaluation",
      "time": "9:30-10:00",
      "patient": {
        "id": 3,
        "area": "urban",
        "firstName": "Nicolis",
        "lastName": "Vuitte",
        "email": "nvuitte2@noaa.gov",
        "gender": "Male",
        "phone": "+258 (242) 940-7383",
        "city": "Maxixe",
        "job": "Teacher",
        "address": "48974 Independence Pass",
        "age": 40,
        "idn": "5623631738",
        "diagnosis": "unavailable"
      },
      "date": "2023-03-08T22:00:00.000Z",
      "history": "",
      "treatment": "",
      "diagnosis": "",
      "clinicalExam": ""
    },
    {
      "id": 112,
      "procedure": "Abdominal ultrasonography",
      "time": "8:00-8:30",
      "patient": {
        "id": 6,
        "area": "urban",
        "firstName": "Cherilyn",
        "lastName": "Imlin",
        "email": "cimlin5@dion.ne.jp",
        "gender": "Female",
        "phone": "+1 (573) 306-8781",
        "city": "Lunenburg",
        "job": "Safety Technician I",
        "address": "388 Valley Edge Street",
        "age": 51,
        "idn": "6609168008",
        "diagnosis": "Kobus defassa"
      },
      "date": "2023-03-09T22:00:00.000Z",
      "history": "",
      "treatment": "",
      "diagnosis": "",
      "clinicalExam": ""
    }
  ],
  "avalaible": [
    {
      "id": 1,
      "date": "2023-03-01T22:00:00Z",
      "slot": "8:00-8:30",
      "isBooked": false
    },
    {
      "id": 2,
      "date": "2023-03-01T22:00:00Z",
      "slot": "8:30-9:00",
      "isBooked": false
    },
    {
      "id": 3,
      "date": "2023-03-01T22:00:00Z",
      "slot": "9:00-9:30",
      "isBooked": false
    },
    {
      "id": 4,
      "date": "2023-03-01T22:00:00Z",
      "slot": "9:30-10:00",
      "isBooked": false
    },
    {
      "id": 5,
      "date": "2023-03-01T22:00:00Z",
      "slot": "10:00-10:30",
      "isBooked": false
    },
    {
      "id": 6,
      "date": "2023-03-01T22:00:00Z",
      "slot": "10:30-11:00",
      "isBooked": false
    },
    {
      "id": 7,
      "date": "2023-03-01T22:00:00Z",
      "slot": "11:00-11:30",
      "isBooked": false
    },
    {
      "id": 8,
      "date": "2023-03-01T22:00:00Z",
      "slot": "11:30-12:00",
      "isBooked": false
    },
    {
      "id": 9,
      "date": "2023-03-01T22:00:00Z",
      "slot": "12:00-12:30",
      "isBooked": false
    },
    {
      "id": 10,
      "date": "2023-03-09T22:00:00Z",
      "slot": "8:00-8:30",
      "isBooked": true
    },
    {
      "id": 11,
      "date": "2023-03-09T22:00:00Z",
      "slot": "8:30-9:00",
      "isBooked": false
    },
    {
      "id": 12,
      "date": "2023-03-09T22:00:00Z",
      "slot": "9:00-9:30",
      "isBooked": false
    },
    {
      "id": 13,
      "date": "2023-03-09T22:00:00Z",
      "slot": "9:30-10:00",
      "isBooked": false
    },
    {
      "id": 14,
      "date": "2023-03-09T22:00:00Z",
      "slot": "10:00-10:30",
      "isBooked": false
    },
    {
      "id": 15,
      "date": "2023-03-09T22:00:00Z",
      "slot": "10:30-11:00",
      "isBooked": false
    },
    {
      "id": 16,
      "date": "2023-03-09T22:00:00Z",
      "slot": "11:00-11:30",
      "isBooked": false
    },
    {
      "id": 17,
      "date": "2023-03-09T22:00:00Z",
      "slot": "11:30-12:00",
      "isBooked": false
    },
    {
      "id": 18,
      "date": "2023-03-09T22:00:00Z",
      "slot": "12:00-12:30",
      "isBooked": false
    },
    {
      "id": 19,
      "date": "2023-03-10T22:00:00Z",
      "slot": "8:00-8:30",
      "isBooked": false
    },
    {
      "id": 20,
      "date": "2023-03-10T22:00:00Z",
      "slot": "8:30-9:00",
      "isBooked": false
    },
    {
      "id": 21,
      "date": "2023-03-10T22:00:00Z",
      "slot": "9:00-9:30",
      "isBooked": false
    },
    {
      "id": 22,
      "date": "2023-03-10T22:00:00Z",
      "slot": "9:30-10:00",
      "isBooked": false
    },
    {
      "id": 23,
      "date": "2023-03-10T22:00:00Z",
      "slot": "10:00-10:30",
      "isBooked": false
    },
    {
      "id": 24,
      "date": "2023-03-10T22:00:00Z",
      "slot": "10:30-11:00",
      "isBooked": false
    },
    {
      "id": 25,
      "date": "2023-03-10T22:00:00Z",
      "slot": "11:00-11:30",
      "isBooked": false
    },
    {
      "id": 26,
      "date": "2023-03-10T22:00:00Z",
      "slot": "11:30-12:00",
      "isBooked": false
    },
    {
      "id": 27,
      "date": "2023-03-10T22:00:00Z",
      "slot": "12:00-12:30",
      "isBooked": false
    },
    {
      "id": 28,
      "date": "2023-03-13T22:00:00Z",
      "slot": "8:00-8:30",
      "isBooked": false
    },
    {
      "id": 29,
      "date": "2023-03-13T22:00:00Z",
      "slot": "8:30-9:00",
      "isBooked": false
    },
    {
      "id": 30,
      "date": "2023-03-13T22:00:00Z",
      "slot": "9:00-9:30",
      "isBooked": false
    },
    {
      "id": 31,
      "date": "2023-03-13T22:00:00Z",
      "slot": "9:30-10:00",
      "isBooked": false
    },
    {
      "id": 32,
      "date": "2023-03-13T22:00:00Z",
      "slot": "10:00-10:30",
      "isBooked": false
    },
    {
      "id": 33,
      "date": "2023-03-13T22:00:00Z",
      "slot": "10:30-11:00",
      "isBooked": false
    },
    {
      "id": 34,
      "date": "2023-03-13T22:00:00Z",
      "slot": "11:00-11:30",
      "isBooked": false
    },
    {
      "id": 35,
      "date": "2023-03-13T22:00:00Z",
      "slot": "11:30-12:00",
      "isBooked": false
    },
    {
      "id": 36,
      "date": "2023-03-13T22:00:00Z",
      "slot": "12:00-12:30",
      "isBooked": false
    },
    {
      "id": 37,
      "date": "2023-03-08T22:00:00Z",
      "slot": "8:00-8:30",
      "isBooked": true
    },
    {
      "id": 38,
      "date": "2023-03-08T22:00:00Z",
      "slot": "8:30-9:00",
      "isBooked": false
    },
    {
      "id": 39,
      "date": "2023-03-08T22:00:00Z",
      "slot": "9:00-9:30",
      "isBooked": false
    },
    {
      "id": 40,
      "date": "2023-03-08T22:00:00Z",
      "slot": "9:30-10:00",
      "isBooked": true
    },
    {
      "id": 41,
      "date": "2023-03-08T22:00:00Z",
      "slot": "10:00-10:30",
      "isBooked": false
    },
    {
      "id": 42,
      "date": "2023-03-08T22:00:00Z",
      "slot": "10:30-11:00",
      "isBooked": false
    },
    {
      "id": 43,
      "date": "2023-03-08T22:00:00Z",
      "slot": "11:00-11:30",
      "isBooked": false
    },
    {
      "id": 44,
      "date": "2023-03-08T22:00:00Z",
      "slot": "11:30-12:00",
      "isBooked": false
    },
    {
      "id": 45,
      "date": "2023-03-08T22:00:00Z",
      "slot": "12:00-12:30",
      "isBooked": false
    },
    {
      "id": 46,
      "date": "2023-03-14T22:00:00Z",
      "slot": "8:00-8:30",
      "isBooked": false
    },
    {
      "id": 47,
      "date": "2023-03-14T22:00:00Z",
      "slot": "8:30-9:00",
      "isBooked": false
    },
    {
      "id": 48,
      "date": "2023-03-14T22:00:00Z",
      "slot": "9:00-9:30",
      "isBooked": false
    },
    {
      "id": 49,
      "date": "2023-03-14T22:00:00Z",
      "slot": "9:30-10:00",
      "isBooked": false
    },
    {
      "id": 50,
      "date": "2023-03-14T22:00:00Z",
      "slot": "10:00-10:30",
      "isBooked": false
    },
    {
      "id": 51,
      "date": "2023-03-14T22:00:00Z",
      "slot": "10:30-11:00",
      "isBooked": false
    },
    {
      "id": 52,
      "date": "2023-03-14T22:00:00Z",
      "slot": "11:00-11:30",
      "isBooked": false
    },
    {
      "id": 53,
      "date": "2023-03-14T22:00:00Z",
      "slot": "11:30-12:00",
      "isBooked": false
    },
    {
      "id": 54,
      "date": "2023-03-14T22:00:00Z",
      "slot": "12:00-12:30",
      "isBooked": false
    },
    {
      "id": 55,
      "date": "2023-03-15T22:00:00Z",
      "slot": "8:00-8:30",
      "isBooked": false
    },
    {
      "id": 56,
      "date": "2023-03-15T22:00:00Z",
      "slot": "8:30-9:00",
      "isBooked": false
    },
    {
      "id": 57,
      "date": "2023-03-15T22:00:00Z",
      "slot": "9:00-9:30",
      "isBooked": false
    },
    {
      "id": 58,
      "date": "2023-03-15T22:00:00Z",
      "slot": "9:30-10:00",
      "isBooked": false
    },
    {
      "id": 59,
      "date": "2023-03-15T22:00:00Z",
      "slot": "10:00-10:30",
      "isBooked": false
    },
    {
      "id": 60,
      "date": "2023-03-15T22:00:00Z",
      "slot": "10:30-11:00",
      "isBooked": false
    },
    {
      "id": 71,
      "date": "2023-03-15T22:00:00Z",
      "slot": "11:00-11:30",
      "isBooked": false
    },
    {
      "id": 72,
      "date": "2023-03-15T22:00:00Z",
      "slot": "11:30-12:00",
      "isBooked": false
    },
    {
      "id": 73,
      "date": "2023-03-15T22:00:00Z",
      "slot": "12:00-12:30",
      "isBooked": false
    },
    {
      "id": 74,
      "date": "2023-03-16T22:00:00Z",
      "slot": "8:00-8:30",
      "isBooked": false
    },
    {
      "id": 75,
      "date": "2023-03-16T22:00:00Z",
      "slot": "8:30-9:00",
      "isBooked": false
    },
    {
      "id": 76,
      "date": "2023-03-16T22:00:00Z",
      "slot": "9:00-9:30",
      "isBooked": false
    },
    {
      "id": 77,
      "date": "2023-03-16T22:00:00Z",
      "slot": "9:30-10:00",
      "isBooked": false
    },
    {
      "id": 78,
      "date": "2023-03-16T22:00:00Z",
      "slot": "10:00-10:30",
      "isBooked": false
    },
    {
      "id": 79,
      "date": "2023-03-16T22:00:00Z",
      "slot": "10:30-11:00",
      "isBooked": false
    },
    {
      "id": 80,
      "date": "2023-03-16T22:00:00Z",
      "slot": "11:00-11:30",
      "isBooked": false
    },
    {
      "id": 81,
      "date": "2023-03-16T22:00:00Z",
      "slot": "11:30-12:00",
      "isBooked": false
    },
    {
      "id": 82,
      "date": "2023-03-16T22:00:00Z",
      "slot": "12:00-12:30",
      "isBooked": false
    },
    {
      "id": 83,
      "date": "2023-03-17T22:00:00Z",
      "slot": "8:00-8:30",
      "isBooked": false
    },
    {
      "id": 84,
      "date": "2023-03-17T22:00:00Z",
      "slot": "8:30-9:00",
      "isBooked": false
    },
    {
      "id": 85,
      "date": "2023-03-17T22:00:00Z",
      "slot": "9:00-9:30",
      "isBooked": false
    },
    {
      "id": 86,
      "date": "2023-03-17T22:00:00Z",
      "slot": "9:30-10:00",
      "isBooked": false
    },
    {
      "id": 87,
      "date": "2023-03-17T22:00:00Z",
      "slot": "10:00-10:30",
      "isBooked": false
    },
    {
      "id": 88,
      "date": "2023-03-17T22:00:00Z",
      "slot": "10:30-11:00",
      "isBooked": false
    },
    {
      "id": 89,
      "date": "2023-03-17T22:00:00Z",
      "slot": "11:00-11:30",
      "isBooked": false
    },
    {
      "id": 90,
      "date": "2023-03-17T22:00:00Z",
      "slot": "11:30-12:00",
      "isBooked": false
    },
    {
      "id": 100,
      "date": "2023-03-17T22:00:00Z",
      "slot": "12:00-12:30",
      "isBooked": false
    }
  ]
}